coderschool/__init__.py
CSfansipan-0.0.2.dist-info/METADATA
CSfansipan-0.0.2.dist-info/WHEEL
CSfansipan-0.0.2.dist-info/top_level.txt
CSfansipan-0.0.2.dist-info/RECORD
