Metadata-Version: 2.1
Name: CSfansipan
Version: 0.0.2
Summary: Coderschool's Full-time MLE package
Home-page: https://github.com/minhanhng-cd/ftmle-package
Author: Nguyen Minh Anh
Author-email: minhanh@coderschool.vn
License: UNKNOWN
Platform: UNKNOWN
Classifier: Programming Language :: Python :: 3
Classifier: License :: OSI Approved :: MIT License
Classifier: Operating System :: OS Independent
